<?xml version = '1.0' encoding = 'UTF-8'?>
<SegmentOraclev10g class="oracle.dbtools.crest.model.design.storage.oracle.v10g.SegmentOraclev10g" name="Storage1" directorySegmentName="seg_0" id="D2CA7C1E-0615-FAE9-6DAE-9DBB39A779EE">
<createdBy>dkuhn</createdBy>
<createdTime>2019-01-19 21:02:28 UTC</createdTime>
<ownerDesignName>ERD</ownerDesignName>
<maxTrans>255</maxTrans>
<scInitialExtent>65536</scInitialExtent>
<scMaxExtents>2147483645</scMaxExtents>
<scNextExtent>1048576</scNextExtent>
</SegmentOraclev10g>